{
  "vehicle_id": "NORA_0006",
  "generated_at": "2026-06-14T15:37:08Z",
  "origin_sid": "s007",
  "dest_sid": null,
  "authorized_speed_ms": 8.3,
  "completed": true,
  "natalie_verdict": "minor_defects",
  "summary": {
    "authorized_segs": 10,
    "executed_segs": 10,
    "skipped_segs": 0,
    "cp_gap_count": 0,
    "speed_deviation_count": 1,
    "total_defects": 1
  },
  "skipped_segs": [

  ],
  "executed_segs": [
    {
      "id": 108,
      "station": "s007",
      "track": "gw_platform",
      "len_mm": 23865,
      "actual_s": 0.931,
      "expected_s": 2.875,
      "actual_ms": 25.63
    },
    {
      "id": 111,
      "station": "s007",
      "track": "gw_platform_out1",
      "len_mm": 10061,
      "actual_s": 1.382,
      "expected_s": 1.212,
      "actual_ms": 7.28
    },
    {
      "id": 112,
      "station": "s007",
      "track": "gw_platform_out2",
      "len_mm": 10139,
      "actual_s": 1.256,
      "expected_s": 1.222,
      "actual_ms": 8.07
    },
    {
      "id": 102,
      "station": "s007",
      "track": "gw_cp_out_lead_1",
      "len_mm": 2500,
      "actual_s": 0.39,
      "expected_s": 0.301,
      "actual_ms": 6.41
    },
    {
      "id": 100,
      "station": "s007",
      "track": "gw_cp_out_1",
      "len_mm": 2500,
      "actual_s": 0.413,
      "expected_s": 0.301,
      "actual_ms": 6.05
    },
    {
      "id": 118,
      "seg_id": "seg_s007_cp1_s006_cp0",
      "len_mm": 97173,
      "actual_s": 11.687,
      "expected_s": 11.708,
      "actual_ms": 8.31
    },
    {
      "id": 67,
      "station": "s006",
      "track": "gw_cp_in_0",
      "len_mm": 2500,
      "actual_s": 0.423,
      "expected_s": 0.301,
      "actual_ms": 5.91
    },
    {
      "id": 69,
      "station": "s006",
      "track": "gw_cp_in_lead_0",
      "len_mm": 2500,
      "actual_s": 0.3,
      "expected_s": 0.301,
      "actual_ms": 8.33
    },
    {
      "id": 81,
      "station": "s006",
      "track": "gw_platform_in1",
      "len_mm": 10061,
      "actual_s": 1.2,
      "expected_s": 1.212,
      "actual_ms": 8.38
    },
    {
      "id": 82,
      "station": "s006",
      "track": "gw_platform_in2",
      "len_mm": 10139,
      "actual_s": 1.251,
      "expected_s": 1.222,
      "actual_ms": 8.11
    }
  ],
  "defects": [
    {
      "type": "speed_deviation",
      "id": 108,
      "station": "s007",
      "track": "gw_platform",
      "authorized_ms": 8.3,
      "actual_ms": 25.63,
      "ratio": 3.09,
      "severity": "moderate"
    }
  ],
  "assessment": {
    "s006": {
      "gw_cp_in_0": {
        "plan": {
          "seq": 7,
          "id": 67,
          "len_mm": 2500,
          "expected_s": 0.301
        },
        "animate": {
          "status": "ok"
        },
        "history": {
          "actual_s": 0.423,
          "actual_ms": 5.91
        }
      },
      "gw_cp_in_lead_0": {
        "plan": {
          "seq": 8,
          "id": 69,
          "len_mm": 2500,
          "expected_s": 0.301
        },
        "animate": {
          "status": "ok"
        },
        "history": {
          "actual_s": 0.3,
          "actual_ms": 8.33
        }
      },
      "gw_platform_in1": {
        "plan": {
          "seq": 9,
          "id": 81,
          "len_mm": 10061,
          "expected_s": 1.212
        },
        "animate": {
          "status": "ok"
        },
        "history": {
          "actual_s": 1.2,
          "actual_ms": 8.38
        }
      },
      "gw_platform_in2": {
        "plan": {
          "seq": 10,
          "id": 82,
          "len_mm": 10139,
          "expected_s": 1.222
        },
        "animate": {
          "status": "ok"
        },
        "history": {
          "actual_s": 1.251,
          "actual_ms": 8.11
        }
      }
    },
    "s007": {
      "gw_platform": {
        "plan": {
          "seq": 1,
          "id": 108,
          "len_mm": 23865,
          "expected_s": 2.875
        },
        "animate": {
          "status": "ok",
          "speed_ratio": 3.09
        },
        "history": {
          "actual_s": 0.931,
          "actual_ms": 25.63
        }
      },
      "gw_platform_out1": {
        "plan": {
          "seq": 2,
          "id": 111,
          "len_mm": 10061,
          "expected_s": 1.212
        },
        "animate": {
          "status": "ok"
        },
        "history": {
          "actual_s": 1.382,
          "actual_ms": 7.28
        }
      },
      "gw_platform_out2": {
        "plan": {
          "seq": 3,
          "id": 112,
          "len_mm": 10139,
          "expected_s": 1.222
        },
        "animate": {
          "status": "ok"
        },
        "history": {
          "actual_s": 1.256,
          "actual_ms": 8.07
        }
      },
      "gw_cp_out_lead_1": {
        "plan": {
          "seq": 4,
          "id": 102,
          "len_mm": 2500,
          "expected_s": 0.301
        },
        "animate": {
          "status": "ok"
        },
        "history": {
          "actual_s": 0.39,
          "actual_ms": 6.41
        }
      },
      "gw_cp_out_1": {
        "plan": {
          "seq": 5,
          "id": 100,
          "len_mm": 2500,
          "expected_s": 0.301
        },
        "animate": {
          "status": "ok"
        },
        "history": {
          "actual_s": 0.413,
          "actual_ms": 6.05
        }
      }
    },
    "connections": {
      "seg_s007_cp1_s006_cp0": {
        "plan": {
          "seq": 6,
          "id": 118,
          "len_mm": 97173,
          "expected_s": 11.708
        },
        "animate": {
          "status": "ok"
        },
        "history": {
          "actual_s": 11.687,
          "actual_ms": 8.31
        }
      }
    }
  }
}