{
  "vehicle_id": "NORA_0003",
  "generated_at": "2026-06-17T02:32:00Z",
  "origin_sid": "",
  "dest_sid": "station_line_end",
  "authorized_speed_ms": 8.3,
  "completed": true,
  "natalie_verdict": "authorized",
  "summary": {
    "authorized_segs": 0,
    "executed_segs": 1,
    "skipped_segs": 0,
    "cp_gap_count": 0,
    "speed_deviation_count": 0,
    "total_defects": 0
  },
  "skipped_segs": [

  ],
  "executed_segs": [
    {
      "seg_id": "station_line_end.hold_loop[6/6]",
      "len_mm": 53065,
      "actual_s": 6.413,
      "expected_s": 6.393,
      "actual_ms": 8.27
    }
  ],
  "defects": [

  ],
  "assessment": {
  }
}