{
  "schema": "jpods-trip-plan-v1",
  "vehicle_id": "NORA_0001",
  "generated_at": "2026-06-14T22:52:11Z",
  "origin_sid": "s004",
  "dest_sid": "s002",
  "authorized_speed_ms": 8.3,
  "seg_count": 19,
  "seq_plan": [
    {
      "seq": 1,
      "seg": "s002.gw_platform"
    },
    {
      "seq": 2,
      "seg": "s002.gw_platform_out1"
    },
    {
      "seq": 3,
      "seg": "s002.gw_platform_out2"
    },
    {
      "seq": 4,
      "seg": "s002.gw_cp_out_lead_1"
    },
    {
      "seq": 5,
      "seg": "s002.gw_cp_out_1"
    },
    {
      "seq": 6,
      "seg": "seg_s002_cp1_s001_cp0"
    },
    {
      "seq": 7,
      "seg": "s001.gw_cp_in_0"
    },
    {
      "seq": 8,
      "seg": "s001.gw_in_0"
    },
    {
      "seq": 9,
      "seg": "s001.gw_c_0_0"
    },
    {
      "seq": 10,
      "seg": "s001.gw_c_3_0"
    },
    {
      "seq": 11,
      "seg": "s001.gw_c_3_3"
    },
    {
      "seq": 12,
      "seg": "s001.gw_c_2_3"
    },
    {
      "seq": 13,
      "seg": "s001.gw_c_2_2"
    },
    {
      "seq": 14,
      "seg": "s001.gw_out_2"
    },
    {
      "seq": 15,
      "seg": "s001.gw_cp_out_2"
    },
    {
      "seq": 16,
      "seg": "seg_s001_cp2_s004_cp0"
    },
    {
      "seq": 17,
      "seg": "s004.gw_cp_in_0"
    },
    {
      "seq": 18,
      "seg": "s004.gw_cp_in_lead_0"
    },
    {
      "seq": 19,
      "seg": "s004.gw_platform_in"
    }
  ],
  "lines": {
    "s001": {
      "gw_cp_in_0": {
        "plan": {
          "seq": 7
        }
      },
      "gw_in_0": {
        "plan": {
          "seq": 8
        }
      },
      "gw_c_0_0": {
        "plan": {
          "seq": 9
        }
      },
      "gw_c_3_0": {
        "plan": {
          "seq": 10
        }
      },
      "gw_c_3_3": {
        "plan": {
          "seq": 11
        }
      },
      "gw_c_2_3": {
        "plan": {
          "seq": 12
        }
      },
      "gw_c_2_2": {
        "plan": {
          "seq": 13
        }
      },
      "gw_out_2": {
        "plan": {
          "seq": 14
        }
      },
      "gw_cp_out_2": {
        "plan": {
          "seq": 15
        }
      }
    },
    "s002": {
      "gw_platform": {
        "plan": {
          "seq": 1
        }
      },
      "gw_platform_out1": {
        "plan": {
          "seq": 2
        }
      },
      "gw_platform_out2": {
        "plan": {
          "seq": 3
        }
      },
      "gw_cp_out_lead_1": {
        "plan": {
          "seq": 4
        }
      },
      "gw_cp_out_1": {
        "plan": {
          "seq": 5
        }
      }
    },
    "s004": {
      "gw_cp_in_0": {
        "plan": {
          "seq": 17
        }
      },
      "gw_cp_in_lead_0": {
        "plan": {
          "seq": 18
        }
      },
      "gw_platform_in": {
        "plan": {
          "seq": 19
        }
      }
    },
    "connections": {
      "seg_s002_cp1_s001_cp0": {
        "plan": {
          "seq": 6
        }
      },
      "seg_s001_cp2_s004_cp0": {
        "plan": {
          "seq": 16
        }
      }
    }
  }
}