{
  "vehicle_id": "NORA_0002",
  "generated_at": "2026-06-07T22:01:38Z",
  "origin_sid": "S004",
  "dest_sid": null,
  "authorized_speed_ms": 8.3,
  "completed": true,
  "natalie_verdict": "minor_defects",
  "summary": {
    "authorized_segs": 22,
    "executed_segs": 22,
    "skipped_segs": 0,
    "cp_gap_count": 4,
    "speed_deviation_count": 1,
    "total_defects": 5
  },
  "skipped_segs": [

  ],
  "executed_segs": [
    {
      "id": 88,
      "station": "s004",
      "track": "gw_platform",
      "len_mm": 11280,
      "actual_s": 0.428,
      "expected_s": 1.359,
      "actual_ms": 26.37
    },
    {
      "id": 90,
      "station": "s004",
      "track": "gw_platform_out",
      "len_mm": 18841,
      "actual_s": 2.303,
      "expected_s": 2.27,
      "actual_ms": 8.18
    },
    {
      "id": 82,
      "station": "s004",
      "track": "gw_cp_out_lead_1",
      "len_mm": 2500,
      "actual_s": 0.299,
      "expected_s": 0.301,
      "actual_ms": 8.35
    },
    {
      "id": 93,
      "station": "s004",
      "track": "gw_uturn_1",
      "len_mm": 5519,
      "actual_s": 0.697,
      "expected_s": 0.665,
      "actual_ms": 7.91
    },
    {
      "id": 78,
      "station": "s004",
      "track": "gw_cp_in_lead_1",
      "len_mm": 2521,
      "actual_s": 0.334,
      "expected_s": 0.304,
      "actual_ms": 7.55
    },
    {
      "id": 83,
      "station": "s004",
      "track": "gw_far_main",
      "len_mm": 63926,
      "actual_s": 7.717,
      "expected_s": 7.702,
      "actual_ms": 8.28
    },
    {
      "id": 81,
      "station": "s004",
      "track": "gw_cp_out_lead_0",
      "len_mm": 2500,
      "actual_s": 0.336,
      "expected_s": 0.301,
      "actual_ms": 7.45
    },
    {
      "id": 79,
      "station": "s004",
      "track": "gw_cp_out_0",
      "len_mm": 2500,
      "actual_s": 0.338,
      "expected_s": 0.301,
      "actual_ms": 7.4
    },
    {
      "id": 99,
      "seg_id": "seg_s004_cp0_s001_cp2",
      "len_mm": 20000,
      "actual_s": 2.405,
      "expected_s": 2.41,
      "actual_ms": 8.32
    },
    {
      "id": 11,
      "station": "s001",
      "track": "gw_cp_in_2",
      "len_mm": 2500,
      "actual_s": 0.294,
      "expected_s": 0.301,
      "actual_ms": 8.52
    },
    {
      "id": 19,
      "station": "s001",
      "track": "gw_in_2",
      "len_mm": 8615,
      "actual_s": 1.078,
      "expected_s": 1.038,
      "actual_ms": 7.99
    },
    {
      "id": 6,
      "station": "s001",
      "track": "gw_c_2_3",
      "len_mm": 968,
      "actual_s": 0.148,
      "expected_s": 0.117,
      "actual_ms": 6.55
    },
    {
      "id": 8,
      "station": "s001",
      "track": "gw_c_3_3",
      "len_mm": 10831,
      "actual_s": 1.315,
      "expected_s": 1.305,
      "actual_ms": 8.24
    },
    {
      "id": 7,
      "station": "s001",
      "track": "gw_c_3_0",
      "len_mm": 968,
      "actual_s": 0.146,
      "expected_s": 0.117,
      "actual_ms": 6.64
    },
    {
      "id": 21,
      "station": "s001",
      "track": "gw_out_0",
      "len_mm": 8596,
      "actual_s": 1.073,
      "expected_s": 1.036,
      "actual_ms": 8.01
    },
    {
      "id": 13,
      "station": "s001",
      "track": "gw_cp_out_0",
      "len_mm": 2500,
      "actual_s": 0.338,
      "expected_s": 0.301,
      "actual_ms": 7.4
    },
    {
      "id": 94,
      "seg_id": "seg_s001_cp0_s002_cp1",
      "len_mm": 21354,
      "actual_s": 2.531,
      "expected_s": 2.573,
      "actual_ms": 8.44
    },
    {
      "id": 34,
      "station": "s002",
      "track": "gw_cp_in_1",
      "len_mm": 2500,
      "actual_s": 0.327,
      "expected_s": 0.301,
      "actual_ms": 7.63
    },
    {
      "id": 36,
      "station": "s002",
      "track": "gw_cp_in_lead_1",
      "len_mm": 2521,
      "actual_s": 0.341,
      "expected_s": 0.304,
      "actual_ms": 7.4
    },
    {
      "id": 41,
      "station": "s002",
      "track": "gw_far_main",
      "len_mm": 63564,
      "actual_s": 7.672,
      "expected_s": 7.658,
      "actual_ms": 8.29
    },
    {
      "id": 39,
      "station": "s002",
      "track": "gw_cp_out_lead_0",
      "len_mm": 2500,
      "actual_s": 0.327,
      "expected_s": 0.301,
      "actual_ms": 7.65
    },
    {
      "id": 37,
      "station": "s002",
      "track": "gw_cp_out_0",
      "len_mm": 2500,
      "actual_s": 0.336,
      "expected_s": 0.301,
      "actual_ms": 7.45
    }
  ],
  "defects": [
    {
      "type": "speed_deviation",
      "id": 88,
      "station": "s004",
      "track": "gw_platform",
      "authorized_ms": 8.3,
      "actual_ms": 26.37,
      "ratio": 3.18,
      "severity": "moderate"
    },
    {
      "type": "cp_gap",
      "seg_id": "99",
      "gap_mm": 1760.0,
      "severity": "moderate"
    },
    {
      "type": "cp_gap",
      "seg_id": "11",
      "gap_mm": 1750.0,
      "severity": "moderate"
    },
    {
      "type": "cp_gap",
      "seg_id": "94",
      "gap_mm": 1760.0,
      "severity": "moderate"
    },
    {
      "type": "cp_gap",
      "seg_id": "34",
      "gap_mm": 1750.0,
      "severity": "moderate"
    }
  ],
  "assessment": {
    "s001": {
      "gw_cp_in_2": {
        "plan": {
          "seq": 10,
          "id": 11,
          "len_mm": 2500,
          "expected_s": 0.301
        },
        "animate": {
          "status": "ok"
        },
        "history": {
          "actual_s": 0.294,
          "actual_ms": 8.52
        }
      },
      "gw_in_2": {
        "plan": {
          "seq": 11,
          "id": 19,
          "len_mm": 8615,
          "expected_s": 1.038
        },
        "animate": {
          "status": "ok"
        },
        "history": {
          "actual_s": 1.078,
          "actual_ms": 7.99
        }
      },
      "gw_c_2_3": {
        "plan": {
          "seq": 12,
          "id": 6,
          "len_mm": 968,
          "expected_s": 0.117
        },
        "animate": {
          "status": "ok"
        },
        "history": {
          "actual_s": 0.148,
          "actual_ms": 6.55
        }
      },
      "gw_c_3_3": {
        "plan": {
          "seq": 13,
          "id": 8,
          "len_mm": 10831,
          "expected_s": 1.305
        },
        "animate": {
          "status": "ok"
        },
        "history": {
          "actual_s": 1.315,
          "actual_ms": 8.24
        }
      },
      "gw_c_3_0": {
        "plan": {
          "seq": 14,
          "id": 7,
          "len_mm": 968,
          "expected_s": 0.117
        },
        "animate": {
          "status": "ok"
        },
        "history": {
          "actual_s": 0.146,
          "actual_ms": 6.64
        }
      },
      "gw_out_0": {
        "plan": {
          "seq": 15,
          "id": 21,
          "len_mm": 8596,
          "expected_s": 1.036
        },
        "animate": {
          "status": "ok"
        },
        "history": {
          "actual_s": 1.073,
          "actual_ms": 8.01
        }
      },
      "gw_cp_out_0": {
        "plan": {
          "seq": 16,
          "id": 13,
          "len_mm": 2500,
          "expected_s": 0.301
        },
        "animate": {
          "status": "ok"
        },
        "history": {
          "actual_s": 0.338,
          "actual_ms": 7.4
        }
      }
    },
    "s002": {
      "gw_cp_in_1": {
        "plan": {
          "seq": 18,
          "id": 34,
          "len_mm": 2500,
          "expected_s": 0.301
        },
        "animate": {
          "status": "ok"
        },
        "history": {
          "actual_s": 0.327,
          "actual_ms": 7.63
        }
      },
      "gw_cp_in_lead_1": {
        "plan": {
          "seq": 19,
          "id": 36,
          "len_mm": 2521,
          "expected_s": 0.304
        },
        "animate": {
          "status": "ok"
        },
        "history": {
          "actual_s": 0.341,
          "actual_ms": 7.4
        }
      },
      "gw_far_main": {
        "plan": {
          "seq": 20,
          "id": 41,
          "len_mm": 63564,
          "expected_s": 7.658
        },
        "animate": {
          "status": "ok"
        },
        "history": {
          "actual_s": 7.672,
          "actual_ms": 8.29
        }
      },
      "gw_cp_out_lead_0": {
        "plan": {
          "seq": 21,
          "id": 39,
          "len_mm": 2500,
          "expected_s": 0.301
        },
        "animate": {
          "status": "ok"
        },
        "history": {
          "actual_s": 0.327,
          "actual_ms": 7.65
        }
      },
      "gw_cp_out_0": {
        "plan": {
          "seq": 22,
          "id": 37,
          "len_mm": 2500,
          "expected_s": 0.301
        },
        "animate": {
          "status": "ok"
        },
        "history": {
          "actual_s": 0.336,
          "actual_ms": 7.45
        }
      }
    },
    "s004": {
      "gw_platform": {
        "plan": {
          "seq": 1,
          "id": 88,
          "len_mm": 11280,
          "expected_s": 1.359
        },
        "animate": {
          "status": "ok",
          "speed_ratio": 3.18
        },
        "history": {
          "actual_s": 0.428,
          "actual_ms": 26.37
        }
      },
      "gw_platform_out": {
        "plan": {
          "seq": 2,
          "id": 90,
          "len_mm": 18841,
          "expected_s": 2.27
        },
        "animate": {
          "status": "ok"
        },
        "history": {
          "actual_s": 2.303,
          "actual_ms": 8.18
        }
      },
      "gw_cp_out_lead_1": {
        "plan": {
          "seq": 3,
          "id": 82,
          "len_mm": 2500,
          "expected_s": 0.301
        },
        "animate": {
          "status": "ok"
        },
        "history": {
          "actual_s": 0.299,
          "actual_ms": 8.35
        }
      },
      "gw_uturn_1": {
        "plan": {
          "seq": 4,
          "id": 93,
          "len_mm": 5519,
          "expected_s": 0.665
        },
        "animate": {
          "status": "ok"
        },
        "history": {
          "actual_s": 0.697,
          "actual_ms": 7.91
        }
      },
      "gw_cp_in_lead_1": {
        "plan": {
          "seq": 5,
          "id": 78,
          "len_mm": 2521,
          "expected_s": 0.304
        },
        "animate": {
          "status": "ok"
        },
        "history": {
          "actual_s": 0.334,
          "actual_ms": 7.55
        }
      },
      "gw_far_main": {
        "plan": {
          "seq": 6,
          "id": 83,
          "len_mm": 63926,
          "expected_s": 7.702
        },
        "animate": {
          "status": "ok"
        },
        "history": {
          "actual_s": 7.717,
          "actual_ms": 8.28
        }
      },
      "gw_cp_out_lead_0": {
        "plan": {
          "seq": 7,
          "id": 81,
          "len_mm": 2500,
          "expected_s": 0.301
        },
        "animate": {
          "status": "ok"
        },
        "history": {
          "actual_s": 0.336,
          "actual_ms": 7.45
        }
      },
      "gw_cp_out_0": {
        "plan": {
          "seq": 8,
          "id": 79,
          "len_mm": 2500,
          "expected_s": 0.301
        },
        "animate": {
          "status": "ok"
        },
        "history": {
          "actual_s": 0.338,
          "actual_ms": 7.4
        }
      }
    },
    "connections": {
      "seg_s004_cp0_s001_cp2": {
        "plan": {
          "seq": 9,
          "id": 99,
          "len_mm": 20000,
          "expected_s": 2.41
        },
        "animate": {
          "status": "ok"
        },
        "history": {
          "actual_s": 2.405,
          "actual_ms": 8.32
        }
      },
      "seg_s001_cp0_s002_cp1": {
        "plan": {
          "seq": 17,
          "id": 94,
          "len_mm": 21354,
          "expected_s": 2.573
        },
        "animate": {
          "status": "ok"
        },
        "history": {
          "actual_s": 2.531,
          "actual_ms": 8.44
        }
      }
    }
  }
}